rhoknp/__init__.py
rhoknp/py.typed
rhoknp/cli/__init__.py
rhoknp/cli/cat.py
rhoknp/cli/cli.py
rhoknp/cli/serve.py
rhoknp/cli/show.py
rhoknp/cli/stats.py
rhoknp/cli/static/css/style.css
rhoknp/cli/static/images/apple-touch-icon.png
rhoknp/cli/static/images/favicon.ico
rhoknp/cli/static/js/script.js
rhoknp/cli/templates/base.jinja2
rhoknp/cli/templates/jumanpp.jinja2
rhoknp/cli/templates/knp.jinja2
rhoknp/cli/templates/kwja.jinja2
rhoknp/cli/templates/components/dependency_parsing.jinja2
rhoknp/cli/templates/components/discourse_parsing.jinja2
rhoknp/cli/templates/components/error.jinja2
rhoknp/cli/templates/components/form.jinja2
rhoknp/cli/templates/components/hide_all_button.jinja2
rhoknp/cli/templates/components/morphological_analysis.jinja2
rhoknp/cli/templates/components/named_entity_recognition.jinja2
rhoknp/cli/templates/components/navbar.jinja2
rhoknp/cli/templates/components/raw_input.jinja2
rhoknp/cli/templates/components/raw_output.jinja2
rhoknp/cli/templates/components/show_all_button.jinja2
rhoknp/cli/templates/components/typo_correction.jinja2
rhoknp/cli/templates/components/word_splitting.jinja2
rhoknp/cohesion/__init__.py
rhoknp/cohesion/argument.py
rhoknp/cohesion/coreference.py
rhoknp/cohesion/discourse.py
rhoknp/cohesion/exophora.py
rhoknp/cohesion/pas.py
rhoknp/cohesion/predicate.py
rhoknp/cohesion/rel.py
rhoknp/processors/__init__.py
rhoknp/processors/jumanpp.py
rhoknp/processors/knp.py
rhoknp/processors/kwja.py
rhoknp/processors/processor.py
rhoknp/processors/senter.py
rhoknp/props/__init__.py
rhoknp/props/dependency.py
rhoknp/props/feature.py
rhoknp/props/memo.py
rhoknp/props/named_entity.py
rhoknp/props/semantics.py
rhoknp/units/__init__.py
rhoknp/units/base_phrase.py
rhoknp/units/clause.py
rhoknp/units/document.py
rhoknp/units/morpheme.py
rhoknp/units/phrase.py
rhoknp/units/sentence.py
rhoknp/units/unit.py
rhoknp/utils/__init__.py
rhoknp/utils/comment.py
rhoknp/utils/reader.py
rhoknp-1.7.1.dist-info/METADATA
rhoknp-1.7.1.dist-info/WHEEL
rhoknp-1.7.1.dist-info/entry_points.txt
rhoknp-1.7.1.dist-info/licenses/AUTHORS.md
rhoknp-1.7.1.dist-info/licenses/LICENSE
rhoknp-1.7.1.dist-info/RECORD
