Metadata-Version: 2.4
Name: rhoknp
Version: 1.7.1
Summary: Yet another Python binding for Juman++/KNP/KWJA
Project-URL: Homepage, https://github.com/ku-nlp/rhoknp
Project-URL: Documentation, https://rhoknp.readthedocs.io/en/latest
Project-URL: Repository, https://github.com/ku-nlp/rhoknp
Project-URL: Issues, https://github.com/ku-nlp/rhoknp/issues
Author-email: Hirokazu Kiyomaru <h.kiyomaru@gmail.com>, Nobuhiro Ueda <ueda@nlp.i.kyoto-u.ac.jp>
Maintainer-email: Hirokazu Kiyomaru <h.kiyomaru@gmail.com>, Nobuhiro Ueda <ueda@nlp.i.kyoto-u.ac.jp>
License-Expression: MIT
License-File: AUTHORS.md
License-File: LICENSE
Keywords: Japanese,Juman++,KNP,KWJA,NLP
Classifier: License :: OSI Approved :: MIT License
Classifier: Natural Language :: Japanese
Classifier: Operating System :: MacOS
Classifier: Operating System :: MacOS :: MacOS X
Classifier: Operating System :: Microsoft :: Windows
Classifier: Operating System :: POSIX :: Linux
Classifier: Programming Language :: Python :: 3
Classifier: Programming Language :: Python :: 3.9
Classifier: Programming Language :: Python :: 3.10
Classifier: Programming Language :: Python :: 3.11
Classifier: Programming Language :: Python :: 3.12
Classifier: Programming Language :: Python :: 3.13
Classifier: Topic :: Scientific/Engineering
Classifier: Topic :: Software Development :: Libraries
Classifier: Topic :: Software Development :: Libraries :: Python Modules
Classifier: Topic :: Text Processing
Classifier: Topic :: Text Processing :: Linguistic
Requires-Python: >=3.9
Requires-Dist: typing-extensions>=4.4; python_version < '3.12'
Provides-Extra: cli
Requires-Dist: fastapi>=0.111.0; extra == 'cli'
Requires-Dist: jinja2>=3.1.4; extra == 'cli'
Requires-Dist: pygments>=2.18.0; extra == 'cli'
Requires-Dist: pyyaml>=6.0; extra == 'cli'
Requires-Dist: rich>=12.6; extra == 'cli'
Requires-Dist: typer-slim>=0.15.2; extra == 'cli'
Requires-Dist: uvicorn>=0.30.0; extra == 'cli'
